oracledb_mcp_server/__init__.py
oracledb_mcp_server/__main__.py
oracledb_mcp_server/utils.py
oracledb_mcp_server-0.1.1.dist-info/licenses/LICENSE
oracledb_mcp_server-0.1.1.dist-info/METADATA
oracledb_mcp_server-0.1.1.dist-info/WHEEL
oracledb_mcp_server-0.1.1.dist-info/entry_points.txt
oracledb_mcp_server-0.1.1.dist-info/top_level.txt
oracledb_mcp_server-0.1.1.dist-info/RECORD
